winglet/__init__.py
winglet-0.0.1.dist-info/licenses/LICENSE
winglet-0.0.1.dist-info/WHEEL
winglet-0.0.1.dist-info/METADATA
winglet-0.0.1.dist-info/RECORD
