Metadata-Version: 2.4
Name: winglet
Version: 0.0.1
Summary: Excel App pool manager for xlwings, managed by lightweight local daemon
Keywords: xlwings,excel,daemon,pool,automation
Author-email: Ryuichi Suzuki <rsuzuki1013@protonmail.com>
Requires-Python: >=3.10
Classifier: License :: OSI Approved :: MIT License
Classifier: Operating System :: Microsoft :: Windows
Classifier: Programming Language :: Python :: 3
Classifier: Programming Language :: Python :: 3.10
Classifier: Programming Language :: Python :: 3.11
Classifier: Programming Language :: Python :: 3.12
Classifier: Programming Language :: Python :: 3.13
Classifier: Topic :: Software Development :: Libraries :: Python Modules
Classifier: Topic :: Office/Business :: Financial :: Spreadsheet
License-File: LICENSE
Requires-Dist: xlwings
Requires-Dist: pywin32
Project-URL: Homepage, https://github.com/RyuichiSuzuki101111/winglet
Project-URL: Issues, https://github.com/RyuichiSuzuki101111/winglet/issues
Project-URL: Source, https://github.com/RyuichiSuzuki101111/winglet
